distributions/Binomialdistribution.py
distributions/Gaussiandistribution.py
distributions/Generaldistribution.py
distributions/__init__.py
distributions16700-0.1.dist-info/DESCRIPTION.rst
distributions16700-0.1.dist-info/METADATA
distributions16700-0.1.dist-info/RECORD
distributions16700-0.1.dist-info/WHEEL
distributions16700-0.1.dist-info/metadata.json
distributions16700-0.1.dist-info/top_level.txt
